<?xml version="1.0" encoding="UTF-8"?>
<!-- Disclaimer: http://www.sbr.gov.au/content/taxonomy_introduction_3_0.htm#Disclaimer -->
<link:linkbase xmlns:link="http://www.xbrl.org/2003/linkbase" xmlns:xsi="http://www.w3.org/2001/XMLSchema-instance" xmlns:tech.01.02="http://sbr.gov.au/fdtn/sbr.01.02.tech" xmlns:xlink="http://www.w3.org/1999/xlink" xmlns:xbrli="http://www.xbrl.org/2003/instance" xsi:schemaLocation="http://sbr.gov.au/fdtn/sbr.01.02.tech ../../../../sbr_au_taxonomy/fdtn/tech.sbr.01.02.xsd">
    <link:roleRef roleURI="http://sbr.gov.au/fdtn/sbr.01.02.tech/legalReference" xlink:type="simple" xlink:href="../../../../sbr_au_taxonomy/fdtn/tech.sbr.01.02.xsd#legalReference"/>
    <link:roleRef roleURI="http://sbr.gov.au/rprt/osrvic/ptmrvic/ptmrvic.0001.calculate.response.02.02/refRole" xlink:type="simple" xlink:href="ptmrvic.0001.calculate.response.02.02.report.xsd#ptmrvic.0001.calculate.response.02.02.refLink"/>
    <link:referenceLink xlink:type="extended" xlink:role="http://sbr.gov.au/rprt/osrvic/ptmrvic/ptmrvic.0001.calculate.response.02.02/refRole">
        <link:loc xlink:type="locator" xlink:href="../../../../sbr_au_taxonomy/icls/py/pyde/pyde.02.00.data.xsd#DE64" xlink:label="loc_DE64"/>
        <link:reference xlink:type="resource" xlink:label="ref_DE64_256709" xlink:role="http://sbr.gov.au/fdtn/sbr.01.02.tech/legalReference"/>
        <link:referenceArc xlink:type="arc" xlink:arcrole="http://www.xbrl.org/2003/arcrole/concept-reference" xlink:from="loc_DE64" xlink:to="ref_DE64_256709"/>
        <link:loc xlink:type="locator" xlink:href="../../../../sbr_au_taxonomy/icls/py/pyde/pyde.02.00.data.xsd#DE55" xlink:label="loc_DE55"/>
        <link:reference xlink:type="resource" xlink:label="ref_DE55_257020" xlink:role="http://sbr.gov.au/fdtn/sbr.01.02.tech/legalReference">
            <tech.01.02:Act>Payroll Tax Act</tech.01.02:Act>
            <tech.01.02:ActYear>2007</tech.01.02:ActYear>
            <tech.01.02:Schedule/>
            <tech.01.02:Chapter/>
            <tech.01.02:Part>1</tech.01.02:Part>
            <tech.01.02:Division/>
            <tech.01.02:Subdivision/>
            <tech.01.02:Section>3</tech.01.02:Section>
            <tech.01.02:FullReferenceText>PART 1 - Definitions; PART 2 - Imposition of payroll tax; PART 7 - Registration and returns</tech.01.02:FullReferenceText>
            <tech.01.02:Paragraph/>
            <tech.01.02:Sub-Section/>
        </link:reference>
        <link:referenceArc xlink:type="arc" xlink:arcrole="http://www.xbrl.org/2003/arcrole/concept-reference" xlink:from="loc_DE55" xlink:to="ref_DE55_257020"/>
        <link:loc xlink:type="locator" xlink:href="../../../../sbr_au_taxonomy/icls/rvc/rvctc/rvctc5.02.00.data.xsd#DE131" xlink:label="loc_DE131"/>
        <link:reference xlink:type="resource" xlink:label="ref_DE131_255902" xlink:role="http://sbr.gov.au/fdtn/sbr.01.02.tech/legalReference">
            <tech.01.02:Act>Payroll Tax Act</tech.01.02:Act>
            <tech.01.02:ActYear>2007</tech.01.02:ActYear>
            <tech.01.02:Schedule/>
            <tech.01.02:Chapter/>
            <tech.01.02:Part>2</tech.01.02:Part>
            <tech.01.02:Division>1</tech.01.02:Division>
            <tech.01.02:Subdivision/>
            <tech.01.02:Section>8</tech.01.02:Section>
            <tech.01.02:Sub-Section/>
            <tech.01.02:Paragraph/>
            <tech.01.02:FullReferenceText>PART 2 - Imposition of tax; Schedule 2 - Calculation of monthly payroll tax</tech.01.02:FullReferenceText>
        </link:reference>
        <link:referenceArc xlink:type="arc" xlink:arcrole="http://www.xbrl.org/2003/arcrole/concept-reference" xlink:from="loc_DE131" xlink:to="ref_DE131_255902"/>
        <link:loc xlink:type="locator" xlink:href="../../../../sbr_au_taxonomy/icls/lr/lrla/lrla.02.00.data.xsd#DE145" xlink:label="loc_DE145"/>
        <link:reference xlink:type="resource" xlink:label="ref_DE145_255848" xlink:role="http://sbr.gov.au/fdtn/sbr.01.02.tech/legalReference">
            <tech.01.02:Act>Payroll Tax Act</tech.01.02:Act>
            <tech.01.02:ActYear>2007</tech.01.02:ActYear>
            <tech.01.02:Schedule/>
            <tech.01.02:Part>2</tech.01.02:Part>
            <tech.01.02:Division>2</tech.01.02:Division>
            <tech.01.02:Subdivision/>
            <tech.01.02:Section>10 to 11</tech.01.02:Section>
            <tech.01.02:Sub-Section/>
            <tech.01.02:Paragraph/>
            <tech.01.02:FullReferenceText>PART 2 - Imposition of tax</tech.01.02:FullReferenceText>
            <tech.01.02:Chapter/>
        </link:reference>
        <link:referenceArc xlink:type="arc" xlink:arcrole="http://www.xbrl.org/2003/arcrole/concept-reference" xlink:from="loc_DE145" xlink:to="ref_DE145_255848"/>
        
        <link:reference xlink:type="resource" xlink:label="ref_DE145_255849" xlink:role="http://sbr.gov.au/fdtn/sbr.01.02.tech/legalReference">
            <tech.01.02:Act>Payroll Tax Act</tech.01.02:Act>
            <tech.01.02:ActYear>2007</tech.01.02:ActYear>
            <tech.01.02:Schedule/>
            <tech.01.02:Chapter/>
            <tech.01.02:Part/>
            <tech.01.02:Division>3</tech.01.02:Division>
            <tech.01.02:Subdivision/>
            <tech.01.02:Section>12</tech.01.02:Section>
            <tech.01.02:FullReferenceText/>
            <tech.01.02:Paragraph/>
            <tech.01.02:Sub-Section/>
        </link:reference>
        <link:referenceArc xlink:type="arc" xlink:arcrole="http://www.xbrl.org/2003/arcrole/concept-reference" xlink:from="loc_DE145" xlink:to="ref_DE145_255849"/>
        
        <link:reference xlink:type="resource" xlink:label="ref_DE145_255850" xlink:role="http://sbr.gov.au/fdtn/sbr.01.02.tech/legalReference">
            <tech.01.02:Act>Payroll Tax Act</tech.01.02:Act>
            <tech.01.02:ActYear>2007</tech.01.02:ActYear>
            <tech.01.02:Schedule/>
            <tech.01.02:Chapter/>
            <tech.01.02:Part>3</tech.01.02:Part>
            <tech.01.02:Division>9</tech.01.02:Division>
            <tech.01.02:Subdivision/>
            <tech.01.02:Section>43 to 47</tech.01.02:Section>
            <tech.01.02:FullReferenceText/>
            <tech.01.02:Paragraph/>
            <tech.01.02:Sub-Section/>
        </link:reference>
        <link:referenceArc xlink:type="arc" xlink:arcrole="http://www.xbrl.org/2003/arcrole/concept-reference" xlink:from="loc_DE145" xlink:to="ref_DE145_255850"/>
        <link:loc xlink:type="locator" xlink:href="../../../../sbr_au_taxonomy/icls/rvc/rvctc/rvctc5.02.00.data.xsd#DE395" xlink:label="loc_DE395"/>
        <link:reference xlink:type="resource" xlink:label="ref_DE395_255882" xlink:role="http://sbr.gov.au/fdtn/sbr.01.02.tech/legalReference">
            <tech.01.02:Act>Payroll Tax Act</tech.01.02:Act>
            <tech.01.02:ActYear>2007</tech.01.02:ActYear>
            <tech.01.02:Schedule/>
            <tech.01.02:Chapter/>
            <tech.01.02:Part>2</tech.01.02:Part>
            <tech.01.02:Division>1</tech.01.02:Division>
            <tech.01.02:Subdivision/>
            <tech.01.02:Section>8</tech.01.02:Section>
            <tech.01.02:Sub-Section/>
            <tech.01.02:Paragraph/>
            <tech.01.02:FullReferenceText>PART 2 - Imposition of tax; PART 5 - Grouping of employers;Schedule 2 - Calculation of monthly payroll tax</tech.01.02:FullReferenceText>
        </link:reference>
        <link:referenceArc xlink:type="arc" xlink:arcrole="http://www.xbrl.org/2003/arcrole/concept-reference" xlink:from="loc_DE395" xlink:to="ref_DE395_255882"/>
        <link:loc xlink:type="locator" xlink:href="../../../../sbr_au_taxonomy/icls/py/pyin/pyin.02.00.data.xsd#DE162" xlink:label="loc_DE162"/>
        <link:reference xlink:type="resource" xlink:label="ref_DE162_255838" xlink:role="http://sbr.gov.au/fdtn/sbr.01.02.tech/legalReference">
            <tech.01.02:Act>Payroll Tax Act</tech.01.02:Act>
            <tech.01.02:ActYear>2007</tech.01.02:ActYear>
            <tech.01.02:Schedule/>
            <tech.01.02:Part>7</tech.01.02:Part>
            <tech.01.02:Division/>
            <tech.01.02:Subdivision/>
            <tech.01.02:Section>87(1)</tech.01.02:Section>
            <tech.01.02:Sub-Section/>
            <tech.01.02:Paragraph>(a)</tech.01.02:Paragraph>
            <tech.01.02:Chapter/>
            <tech.01.02:FullReferenceText>PART 7 - Registration and Return.</tech.01.02:FullReferenceText>
        </link:reference>
        <link:referenceArc xlink:type="arc" xlink:arcrole="http://www.xbrl.org/2003/arcrole/concept-reference" xlink:from="loc_DE162" xlink:to="ref_DE162_255838"/>
        <link:loc xlink:type="locator" xlink:href="../../../../sbr_au_taxonomy/icls/rvc/rvctc/rvctc3.02.00.data.xsd#DE868" xlink:label="loc_DE868"/>
        <link:reference xlink:type="resource" xlink:label="ref_DE868_256739" xlink:role="http://sbr.gov.au/fdtn/sbr.01.02.tech/legalReference">
            <tech.01.02:Act>Payroll Tax Act</tech.01.02:Act>
            <tech.01.02:ActYear>2007</tech.01.02:ActYear>
            <tech.01.02:Schedule/>
            <tech.01.02:Chapter/>
            <tech.01.02:Part>2</tech.01.02:Part>
            <tech.01.02:Division>1</tech.01.02:Division>
            <tech.01.02:Subdivision/>
            <tech.01.02:Section>8</tech.01.02:Section>
            <tech.01.02:Sub-Section/>
            <tech.01.02:Paragraph/>
            <tech.01.02:FullReferenceText>PART 2 - Imposition of tax; Schedule 2 - Calculation of monthly payroll tax</tech.01.02:FullReferenceText>
        </link:reference>
        <link:referenceArc xlink:type="arc" xlink:arcrole="http://www.xbrl.org/2003/arcrole/concept-reference" xlink:from="loc_DE868" xlink:to="ref_DE868_256739"/>
        <link:loc xlink:type="locator" xlink:href="../../../../sbr_au_taxonomy/icls/rvc/rvctc/rvctc5.02.00.data.xsd#DE502" xlink:label="loc_DE502"/>
        <link:reference xlink:type="resource" xlink:label="ref_DE502_255897" xlink:role="http://sbr.gov.au/fdtn/sbr.01.02.tech/legalReference">
            <tech.01.02:Act>Payroll Tax Act</tech.01.02:Act>
            <tech.01.02:ActYear>2007</tech.01.02:ActYear>
            <tech.01.02:Schedule/>
            <tech.01.02:Part>2</tech.01.02:Part>
            <tech.01.02:Division>2</tech.01.02:Division>
            <tech.01.02:Subdivision/>
            <tech.01.02:Section>10 to 12</tech.01.02:Section>
            <tech.01.02:Sub-Section/>
            <tech.01.02:Paragraph/>
            <tech.01.02:FullReferenceText>PART 2 - Imposition of tax</tech.01.02:FullReferenceText>
            <tech.01.02:Chapter/>
        </link:reference>
        <link:referenceArc xlink:type="arc" xlink:arcrole="http://www.xbrl.org/2003/arcrole/concept-reference" xlink:from="loc_DE502" xlink:to="ref_DE502_255897"/>
        <link:loc xlink:type="locator" xlink:href="../../../../sbr_au_taxonomy/icls/py/pyid/pyid.02.00.data.xsd#DE765" xlink:label="loc_DE765"/>
        <link:reference xlink:type="resource" xlink:label="ref_DE765_255830" xlink:role="http://sbr.gov.au/fdtn/sbr.01.02.tech/legalReference">
            <tech.01.02:Act>Payroll Tax Act</tech.01.02:Act>
            <tech.01.02:ActYear>2007</tech.01.02:ActYear>
            <tech.01.02:Part>5</tech.01.02:Part>
            <tech.01.02:Chapter/>
            <tech.01.02:Division/>
            <tech.01.02:FullReferenceText/>
            <tech.01.02:Paragraph/>
            <tech.01.02:Schedule/>
            <tech.01.02:Section/>
            <tech.01.02:Subdivision/>
            <tech.01.02:Sub-Section/>
        </link:reference>
        <link:referenceArc xlink:type="arc" xlink:arcrole="http://www.xbrl.org/2003/arcrole/concept-reference" xlink:from="loc_DE765" xlink:to="ref_DE765_255830"/>
        <link:loc xlink:type="locator" xlink:href="../../../../sbr_au_taxonomy/icls/rvc/rvctc/rvctc5.02.03.data.xsd#DE3161" xlink:label="loc_DE3161"/>
        <link:reference xlink:type="resource" xlink:label="ref_DE3161_255891" xlink:role="http://sbr.gov.au/fdtn/sbr.01.02.tech/legalReference">
            <tech.01.02:Act>Payroll Tax Act</tech.01.02:Act>
            <tech.01.02:ActYear>2007</tech.01.02:ActYear>
            <tech.01.02:Schedule>2</tech.01.02:Schedule>
            <tech.01.02:Chapter/>
            <tech.01.02:Part>2</tech.01.02:Part>
            <tech.01.02:Division>5</tech.01.02:Division>
            <tech.01.02:FullReferenceText/>
            <tech.01.02:Paragraph/>
            <tech.01.02:Section/>
            <tech.01.02:Subdivision/>
            <tech.01.02:Sub-Section/>
        </link:reference>
        <link:referenceArc xlink:type="arc" xlink:arcrole="http://www.xbrl.org/2003/arcrole/concept-reference" xlink:from="loc_DE3161" xlink:to="ref_DE3161_255891"/>
        
        <link:reference xlink:type="resource" xlink:label="ref_DE3161_255892" xlink:role="http://sbr.gov.au/fdtn/sbr.01.02.tech/legalReference">
            <tech.01.02:Act>Payroll Tax Act</tech.01.02:Act>
            <tech.01.02:ActYear>2007</tech.01.02:ActYear>
            <tech.01.02:Schedule>2</tech.01.02:Schedule>
            <tech.01.02:Chapter/>
            <tech.01.02:Part>3</tech.01.02:Part>
            <tech.01.02:Division>9</tech.01.02:Division>
            <tech.01.02:FullReferenceText/>
            <tech.01.02:Paragraph/>
            <tech.01.02:Section/>
            <tech.01.02:Subdivision/>
            <tech.01.02:Sub-Section/>
        </link:reference>
        <link:referenceArc xlink:type="arc" xlink:arcrole="http://www.xbrl.org/2003/arcrole/concept-reference" xlink:from="loc_DE3161" xlink:to="ref_DE3161_255892"/>
    </link:referenceLink>
</link:linkbase>
