<?xml version="1.0" encoding="UTF-8"?>
<!--Disclaimer: http://www.sbr.gov.au/content/taxonomy_introduction_3_0.htm#Disclaimer -->
<link:linkbase xmlns:link="http://www.xbrl.org/2003/linkbase" xmlns:xbrldt="http://xbrl.org/2005/xbrldt" xmlns:xbrli="http://www.xbrl.org/2003/instance" xmlns:xlink="http://www.w3.org/1999/xlink" xmlns:xsi="http://www.w3.org/2001/XMLSchema-instance" xsi:schemaLocation="http://www.xbrl.org/2003/linkbase http://www.xbrl.org/2003/xbrl-linkbase-2003-12-31.xsd">
	<link:roleRef xlink:type="simple" roleURI="http://sbr.gov.au/rprt/apra/arf/arf_116_0_14/arf_116_0_14.0001.lodge.request.02.02/presRole" xlink:href="arf_116_0_14.0001.lodge.request.02.02.xsd#arf_116_0_14.0001.lodge.request.02.02.presLink"/>
	<link:presentationLink xlink:type="extended" xlink:role="http://sbr.gov.au/rprt/apra/arf/arf_116_0_14/arf_116_0_14.0001.lodge.request.02.02/presRole">
		<link:loc xlink:type="locator" xlink:href="arf_116_0_14.0001.lodge.request.02.02.xsd#arf_116_0_14_ReportHeader" xlink:label="ReportHeader" xlink:title="ReportHeader"/>
		<link:loc xlink:type="locator" xlink:href="../../../../../sbr_au_taxonomy/icls/py/pyde/pyde.02.00.data.xsd#DE55" xlink:label="entityName" xlink:title="entityName"/>
		<link:presentationArc xlink:type="arc" xlink:arcrole="http://www.xbrl.org/2003/arcrole/parent-child" xlink:from="ReportHeader" xlink:to="entityName" xlink:title="presentation: ReportHeader to entityName" order="1.0"/>
		<link:loc xlink:type="locator" xlink:href="../../../../../sbr_au_taxonomy/icls/py/pyin/pyin.02.00.data.xsd#DE815" xlink:label="startDate" xlink:title="startDate"/>
		<link:presentationArc xlink:type="arc" xlink:arcrole="http://www.xbrl.org/2003/arcrole/parent-child" xlink:from="ReportHeader" xlink:to="startDate" xlink:title="presentation: ReportHeader to startDate" order="2.0"/>
		<link:loc xlink:type="locator" xlink:href="../../../../../sbr_au_taxonomy/icls/py/pyin/pyin.02.00.data.xsd#DE816" xlink:label="endDate" xlink:title="endDate"/>
		<link:presentationArc xlink:type="arc" xlink:arcrole="http://www.xbrl.org/2003/arcrole/parent-child" xlink:from="ReportHeader" xlink:to="endDate" xlink:title="presentation: ReportHeader to endDate" order="3.0"/>
		<link:loc xlink:type="locator" xlink:href="../../../../../sbr_au_taxonomy/icls/py/pyin/pyin.02.09.data.xsd#DE4880" xlink:label="returnIdentifier" xlink:title="returnIdentifier"/>
		<link:presentationArc xlink:type="arc" xlink:arcrole="http://www.xbrl.org/2003/arcrole/parent-child" xlink:from="ReportHeader" xlink:to="returnIdentifier" xlink:title="presentation: ReportHeader to returnIdentifier" order="4.0"/>
		<link:loc xlink:type="locator" xlink:href="../../../../../sbr_au_taxonomy/icls/py/pyin/pyin.02.09.data.xsd#DE4882" xlink:label="returnVersion" xlink:title="returnVersion"/>
		<link:presentationArc xlink:type="arc" xlink:arcrole="http://www.xbrl.org/2003/arcrole/parent-child" xlink:from="ReportHeader" xlink:to="returnVersion" xlink:title="presentation: ReportHeader to returnVersion" order="5.0"/>
		<link:loc xlink:type="locator" xlink:href="../../../../../sbr_au_taxonomy/icls/py/pyin/pyin.02.09.data.xsd#DE4874" xlink:label="returnName" xlink:title="returnName"/>
		<link:presentationArc xlink:type="arc" xlink:arcrole="http://www.xbrl.org/2003/arcrole/parent-child" xlink:from="ReportHeader" xlink:to="returnName" xlink:title="presentation: ReportHeader to returnName" order="6.0"/>
		<link:loc xlink:type="locator" xlink:href="../../../../../sbr_au_taxonomy/icls/py/pyin/pyin.02.02.data.xsd#DE833" xlink:label="formIdentifier" xlink:title="formIdentifier"/>
		<link:presentationArc xlink:type="arc" xlink:arcrole="http://www.xbrl.org/2003/arcrole/parent-child" xlink:from="ReportHeader" xlink:to="formIdentifier" xlink:title="presentation: ReportHeader to formIdentifier" order="7.0"/>
		<link:loc xlink:type="locator" xlink:href="../../../../../sbr_au_taxonomy/icls/py/pyin/pyin.02.00.data.xsd#DE3146" xlink:label="formVersion" xlink:title="formVersion"/>
		<link:presentationArc xlink:type="arc" xlink:arcrole="http://www.xbrl.org/2003/arcrole/parent-child" xlink:from="ReportHeader" xlink:to="formVersion" xlink:title="presentation: ReportHeader to formVersion" order="8.0"/>
		<link:loc xlink:type="locator" xlink:href="../../../../../sbr_au_taxonomy/icls/py/pyin/pyin.02.09.data.xsd#DE4879" xlink:label="formName" xlink:title="formName"/>
		<link:presentationArc xlink:type="arc" xlink:arcrole="http://www.xbrl.org/2003/arcrole/parent-child" xlink:from="ReportHeader" xlink:to="formName" xlink:title="presentation: ReportHeader to formName" order="9.0"/>
		<link:loc xlink:type="locator" xlink:href="../../../../../sbr_au_taxonomy/icls/baf/bafot/bafot.02.05.data.xsd#DE4875" xlink:label="reportingConsolidationIdentifier" xlink:title="reportingConsolidationIdentifier"/>
		<link:presentationArc xlink:type="arc" xlink:arcrole="http://www.xbrl.org/2003/arcrole/parent-child" xlink:from="ReportHeader" xlink:to="reportingConsolidationIdentifier" xlink:title="presentation: ReportHeader to reportingConsolidationIdentifier" order="10.0"/>
		<link:loc xlink:type="locator" xlink:href="../../../../../sbr_au_taxonomy/icls/baf/bafot/bafot.02.05.data.xsd#DE4877" xlink:label="reportingConsolidationType" xlink:title="reportingConsolidationType"/>
		<link:presentationArc xlink:type="arc" xlink:arcrole="http://www.xbrl.org/2003/arcrole/parent-child" xlink:from="ReportHeader" xlink:to="reportingConsolidationType" xlink:title="presentation: ReportHeader to reportingConsolidationType" order="11.0"/>
		<link:loc xlink:type="locator" xlink:href="../../../../../sbr_au_taxonomy/icls/baf/bafot/bafot.02.05.data.xsd#DE4878" xlink:label="reportingConsolidationSubType" xlink:title="reportingConsolidationSubType"/>
		<link:presentationArc xlink:type="arc" xlink:arcrole="http://www.xbrl.org/2003/arcrole/parent-child" xlink:from="ReportHeader" xlink:to="reportingConsolidationSubType" xlink:title="presentation: ReportHeader to reportingConsolidationSubType" order="12.0"/>
		<link:loc xlink:type="locator" xlink:href="../../../../../sbr_au_taxonomy/icls/baf/bafot/bafot.02.05.data.xsd#DE4876" xlink:label="reportingConsolidationName" xlink:title="reportingConsolidationName"/>
		<link:presentationArc xlink:type="arc" xlink:arcrole="http://www.xbrl.org/2003/arcrole/parent-child" xlink:from="ReportHeader" xlink:to="reportingConsolidationName" xlink:title="presentation: ReportHeader to reportingConsolidationName" order="13.0"/>
		<link:loc xlink:type="locator" xlink:href="arf_116_0_14.0001.lodge.request.02.02.xsd#arf_116_0_14_ReportContent" xlink:label="ReportContent" xlink:title="ReportContent"/>
		<link:loc xlink:type="locator" xlink:href="../../../../../sbr_au_taxonomy/icls/baf/bafot/bafot.02.06.data.xsd#DE8051" xlink:label="FinancialRisk.Market.DailyLossFifthLargest.Amount" xlink:title="FinancialRisk.Market.DailyLossFifthLargest.Amount"/>
		<link:presentationArc xlink:type="arc" xlink:arcrole="http://www.xbrl.org/2003/arcrole/parent-child" xlink:from="ReportContent" xlink:to="FinancialRisk.Market.DailyLossFifthLargest.Amount" xlink:title="presentation: ReportContent to FinancialRisk.Market.DailyLossFifthLargest.Amount" order="1001.0"/>
		<link:loc xlink:type="locator" xlink:href="../../../../../sbr_au_taxonomy/icls/baf/bafot/bafot.02.06.data.xsd#DE8061" xlink:label="FinancialRisk.Market.DailyLossFifthLargest.Date" xlink:title="FinancialRisk.Market.DailyLossFifthLargest.Date"/>
		<link:presentationArc xlink:type="arc" xlink:arcrole="http://www.xbrl.org/2003/arcrole/parent-child" xlink:from="ReportContent" xlink:to="FinancialRisk.Market.DailyLossFifthLargest.Date" xlink:title="presentation: ReportContent to FinancialRisk.Market.DailyLossFifthLargest.Date" order="1002.0"/>
		<link:loc xlink:type="locator" xlink:href="../../../../../sbr_au_taxonomy/icls/baf/bafot/bafot.02.06.data.xsd#DE8050" xlink:label="FinancialRisk.Market.DailyLossFourthLargest.Amount" xlink:title="FinancialRisk.Market.DailyLossFourthLargest.Amount"/>
		<link:presentationArc xlink:type="arc" xlink:arcrole="http://www.xbrl.org/2003/arcrole/parent-child" xlink:from="ReportContent" xlink:to="FinancialRisk.Market.DailyLossFourthLargest.Amount" xlink:title="presentation: ReportContent to FinancialRisk.Market.DailyLossFourthLargest.Amount" order="1003.0"/>
		<link:loc xlink:type="locator" xlink:href="../../../../../sbr_au_taxonomy/icls/baf/bafot/bafot.02.06.data.xsd#DE8060" xlink:label="FinancialRisk.Market.DailyLossFourthLargest.Date" xlink:title="FinancialRisk.Market.DailyLossFourthLargest.Date"/>
		<link:presentationArc xlink:type="arc" xlink:arcrole="http://www.xbrl.org/2003/arcrole/parent-child" xlink:from="ReportContent" xlink:to="FinancialRisk.Market.DailyLossFourthLargest.Date" xlink:title="presentation: ReportContent to FinancialRisk.Market.DailyLossFourthLargest.Date" order="1004.0"/>
		<link:loc xlink:type="locator" xlink:href="../../../../../sbr_au_taxonomy/icls/baf/bafot/bafot.02.06.data.xsd#DE8047" xlink:label="FinancialRisk.Market.DailyLossLargest.Amount" xlink:title="FinancialRisk.Market.DailyLossLargest.Amount"/>
		<link:presentationArc xlink:type="arc" xlink:arcrole="http://www.xbrl.org/2003/arcrole/parent-child" xlink:from="ReportContent" xlink:to="FinancialRisk.Market.DailyLossLargest.Amount" xlink:title="presentation: ReportContent to FinancialRisk.Market.DailyLossLargest.Amount" order="1005.0"/>
		<link:loc xlink:type="locator" xlink:href="../../../../../sbr_au_taxonomy/icls/baf/bafot/bafot.02.06.data.xsd#DE8057" xlink:label="FinancialRisk.Market.DailyLossLargest.Date" xlink:title="FinancialRisk.Market.DailyLossLargest.Date"/>
		<link:presentationArc xlink:type="arc" xlink:arcrole="http://www.xbrl.org/2003/arcrole/parent-child" xlink:from="ReportContent" xlink:to="FinancialRisk.Market.DailyLossLargest.Date" xlink:title="presentation: ReportContent to FinancialRisk.Market.DailyLossLargest.Date" order="1006.0"/>
		<link:loc xlink:type="locator" xlink:href="../../../../../sbr_au_taxonomy/icls/baf/bafot/bafot.02.06.data.xsd#DE8048" xlink:label="FinancialRisk.Market.DailyLossSecondLargest.Amount" xlink:title="FinancialRisk.Market.DailyLossSecondLargest.Amount"/>
		<link:presentationArc xlink:type="arc" xlink:arcrole="http://www.xbrl.org/2003/arcrole/parent-child" xlink:from="ReportContent" xlink:to="FinancialRisk.Market.DailyLossSecondLargest.Amount" xlink:title="presentation: ReportContent to FinancialRisk.Market.DailyLossSecondLargest.Amount" order="1007.0"/>
		<link:loc xlink:type="locator" xlink:href="../../../../../sbr_au_taxonomy/icls/baf/bafot/bafot.02.06.data.xsd#DE8058" xlink:label="FinancialRisk.Market.DailyLossSecondLargest.Date" xlink:title="FinancialRisk.Market.DailyLossSecondLargest.Date"/>
		<link:presentationArc xlink:type="arc" xlink:arcrole="http://www.xbrl.org/2003/arcrole/parent-child" xlink:from="ReportContent" xlink:to="FinancialRisk.Market.DailyLossSecondLargest.Date" xlink:title="presentation: ReportContent to FinancialRisk.Market.DailyLossSecondLargest.Date" order="1008.0"/>
		<link:loc xlink:type="locator" xlink:href="../../../../../sbr_au_taxonomy/icls/baf/bafot/bafot.02.06.data.xsd#DE8049" xlink:label="FinancialRisk.Market.DailyLossThirdLargest.Amount" xlink:title="FinancialRisk.Market.DailyLossThirdLargest.Amount"/>
		<link:presentationArc xlink:type="arc" xlink:arcrole="http://www.xbrl.org/2003/arcrole/parent-child" xlink:from="ReportContent" xlink:to="FinancialRisk.Market.DailyLossThirdLargest.Amount" xlink:title="presentation: ReportContent to FinancialRisk.Market.DailyLossThirdLargest.Amount" order="1009.0"/>
		<link:loc xlink:type="locator" xlink:href="../../../../../sbr_au_taxonomy/icls/baf/bafot/bafot.02.06.data.xsd#DE8059" xlink:label="FinancialRisk.Market.DailyLossThirdLargest.Date" xlink:title="FinancialRisk.Market.DailyLossThirdLargest.Date"/>
		<link:presentationArc xlink:type="arc" xlink:arcrole="http://www.xbrl.org/2003/arcrole/parent-child" xlink:from="ReportContent" xlink:to="FinancialRisk.Market.DailyLossThirdLargest.Date" xlink:title="presentation: ReportContent to FinancialRisk.Market.DailyLossThirdLargest.Date" order="1010.0"/>
		<link:loc xlink:type="locator" xlink:href="../../../../../sbr_au_taxonomy/icls/baf/bafot/bafot.02.06.data.xsd#DE8056" xlink:label="FinancialRisk.Market.VaRForDateOfFifthLargestDailyLoss.Amount" xlink:title="FinancialRisk.Market.VaRForDateOfFifthLargestDailyLoss.Amount"/>
		<link:presentationArc xlink:type="arc" xlink:arcrole="http://www.xbrl.org/2003/arcrole/parent-child" xlink:from="ReportContent" xlink:to="FinancialRisk.Market.VaRForDateOfFifthLargestDailyLoss.Amount" xlink:title="presentation: ReportContent to FinancialRisk.Market.VaRForDateOfFifthLargestDailyLoss.Amount" order="1011.0"/>
		<link:loc xlink:type="locator" xlink:href="../../../../../sbr_au_taxonomy/icls/baf/bafot/bafot.02.06.data.xsd#DE8055" xlink:label="FinancialRisk.Market.VaRForDateOfFourthLargestDailyLoss.Amount" xlink:title="FinancialRisk.Market.VaRForDateOfFourthLargestDailyLoss.Amount"/>
		<link:presentationArc xlink:type="arc" xlink:arcrole="http://www.xbrl.org/2003/arcrole/parent-child" xlink:from="ReportContent" xlink:to="FinancialRisk.Market.VaRForDateOfFourthLargestDailyLoss.Amount" xlink:title="presentation: ReportContent to FinancialRisk.Market.VaRForDateOfFourthLargestDailyLoss.Amount" order="1012.0"/>
		<link:loc xlink:type="locator" xlink:href="../../../../../sbr_au_taxonomy/icls/baf/bafot/bafot.02.06.data.xsd#DE8052" xlink:label="FinancialRisk.Market.VaRForDateOfLargestDailyLoss.Amount" xlink:title="FinancialRisk.Market.VaRForDateOfLargestDailyLoss.Amount"/>
		<link:presentationArc xlink:type="arc" xlink:arcrole="http://www.xbrl.org/2003/arcrole/parent-child" xlink:from="ReportContent" xlink:to="FinancialRisk.Market.VaRForDateOfLargestDailyLoss.Amount" xlink:title="presentation: ReportContent to FinancialRisk.Market.VaRForDateOfLargestDailyLoss.Amount" order="1013.0"/>
		<link:loc xlink:type="locator" xlink:href="../../../../../sbr_au_taxonomy/icls/baf/bafot/bafot.02.06.data.xsd#DE8053" xlink:label="FinancialRisk.Market.VaRForDateOfSecondLargestDailyLoss.Amount" xlink:title="FinancialRisk.Market.VaRForDateOfSecondLargestDailyLoss.Amount"/>
		<link:presentationArc xlink:type="arc" xlink:arcrole="http://www.xbrl.org/2003/arcrole/parent-child" xlink:from="ReportContent" xlink:to="FinancialRisk.Market.VaRForDateOfSecondLargestDailyLoss.Amount" xlink:title="presentation: ReportContent to FinancialRisk.Market.VaRForDateOfSecondLargestDailyLoss.Amount" order="1014.0"/>
		<link:loc xlink:type="locator" xlink:href="../../../../../sbr_au_taxonomy/icls/baf/bafot/bafot.02.06.data.xsd#DE8054" xlink:label="FinancialRisk.Market.VaRForDateOfThirdLargestDailyLoss.Amount" xlink:title="FinancialRisk.Market.VaRForDateOfThirdLargestDailyLoss.Amount"/>
		<link:presentationArc xlink:type="arc" xlink:arcrole="http://www.xbrl.org/2003/arcrole/parent-child" xlink:from="ReportContent" xlink:to="FinancialRisk.Market.VaRForDateOfThirdLargestDailyLoss.Amount" xlink:title="presentation: ReportContent to FinancialRisk.Market.VaRForDateOfThirdLargestDailyLoss.Amount" order="1015.0"/>
	</link:presentationLink>
</link:linkbase>